src/__init__.py
egaki-0.0.0.dist-info/METADATA
egaki-0.0.0.dist-info/WHEEL
egaki-0.0.0.dist-info/licenses/LICENSE
egaki-0.0.0.dist-info/RECORD
