Metadata-Version: 2.1
Name: Egaki
Version: 0.0.0
Summary: A programming language with a syntax entirely in emoji, interpreted to Python at runtime
Project-URL: Homepage, https://www.github.com/anth-volk/egaki
Project-URL: Bug Tracker, https://www.github.com/anth-volk/egaki/issues
Author-email: Anthony Volk <anth.volk@gmail.com>
License-File: LICENSE
Classifier: Development Status :: 1 - Planning
Classifier: License :: OSI Approved :: MIT License
Classifier: Operating System :: OS Independent
Classifier: Programming Language :: Python :: 3
Requires-Python: >=3.9
